mimicel/CELLexer.py
mimicel/CELParser.py
mimicel/CELVisitor.py
mimicel/__init__.py
mimicel/api.py
mimicel/cel_ast_builder.py
mimicel/cel_checker.py
mimicel/cel_library.py
mimicel/cel_values/__init__.py
mimicel/cel_values/base.py
mimicel/cel_values/cel_types.py
mimicel/cel_values/composites.py
mimicel/cel_values/constants.py
mimicel/cel_values/errors.py
mimicel/cel_values/primitives.py
mimicel/cel_values/well_known_types.py
mimicel/context.py
mimicel/duration/CelDurationLexer.py
mimicel/duration/CelDurationParser.py
mimicel/duration/CelDurationVisitor.py
mimicel/duration/__init__.py
mimicel/duration/duration_visitor.py
mimicel/eval_pb.py
mimicel/joda/JodaLexer.py
mimicel/joda/JodaParser.py
mimicel/joda/JodaVisitor.py
mimicel/joda/__init__.py
mimicel/joda/joda_visitor.py
mimicel/literal_registry_pb.py
mimicel/macro_registry_pb.py
mimicel/standard_definitions/__init__.py
mimicel/standard_definitions/conversions.py
mimicel/standard_definitions/defs_internal.py
mimicel/standard_definitions/defs_operator_arithmetic.py
mimicel/standard_definitions/defs_operator_comparison.py
mimicel/standard_definitions/defs_operator_misc.py
mimicel/standard_definitions/defs_standard_functions.py
mimicel/standard_definitions/defs_type_conversion.py
mimicel/standard_definitions/functions.py
mimicel/standard_definitions/helpers.py
mimicel/standard_definitions/operators.py
mimicel/type_registry.py
mimicel/unquote.py
mimicel-0.0.1.dist-info/WHEEL
mimicel-0.0.1.dist-info/METADATA
mimicel-0.0.1.dist-info/LICENSE
mimicel-0.0.1.dist-info/RECORD
