Metadata-Version: 2.1
Name: mimicel
Author: Shuhei Tanuma
Author-email: shuhei.tanuma@gmail.com
Home-page: https://github.com/chobie/mimicel
License: Apache-2.0
Summary: A CEL (Common Expression Language) compliant expression engine for Python
Requires-Python: >=3.10
Requires-Dist: antlr4-python3-runtime>=4.13.2
Requires-Dist: protobuf>=6.30.2
Requires-Dist: google-re2>=1.1.20240702
Requires-Dist: googleapis-common-protos>=1.70.0
Provides-Extra: dev
Requires-Dist: mypy-protobuf>=3.6.0; extra == 'dev'
Requires-Dist: pytest>=8.3.5; extra == 'dev'
Version: 0.0.1
